OpencvTuxiangchuliXuexiShouceChuyiFix1/README.md
OpencvTuxiangchuliXuexiShouceChuyiFix1/__init__.py
OpencvTuxiangchuliXuexiShouceChuyiFix1/__main__.py
OpencvTuxiangchuliXuexiShouceChuyiFix1/file.epub
OpencvTuxiangchuliXuexiShouceChuyiFix1/index.html
OpencvTuxiangchuliXuexiShouceChuyiFix1/css/__init__.py
OpencvTuxiangchuliXuexiShouceChuyiFix1/css/annotations.css
OpencvTuxiangchuliXuexiShouceChuyiFix1/css/main.css
OpencvTuxiangchuliXuexiShouceChuyiFix1/css/normalize.css
OpencvTuxiangchuliXuexiShouceChuyiFix1/css/popup.css
OpencvTuxiangchuliXuexiShouceChuyiFix1/font/__init__.py
OpencvTuxiangchuliXuexiShouceChuyiFix1/font/fontello.eot
OpencvTuxiangchuliXuexiShouceChuyiFix1/font/fontello.svg
OpencvTuxiangchuliXuexiShouceChuyiFix1/font/fontello.ttf
OpencvTuxiangchuliXuexiShouceChuyiFix1/font/fontello.woff
OpencvTuxiangchuliXuexiShouceChuyiFix1/img/__init__.py
OpencvTuxiangchuliXuexiShouceChuyiFix1/img/annotator-glyph-sprite.png
OpencvTuxiangchuliXuexiShouceChuyiFix1/img/annotator-icon-sprite.png
OpencvTuxiangchuliXuexiShouceChuyiFix1/img/apple-touch-icon.png
OpencvTuxiangchuliXuexiShouceChuyiFix1/img/cancelfullscreen.png
OpencvTuxiangchuliXuexiShouceChuyiFix1/img/close.png
OpencvTuxiangchuliXuexiShouceChuyiFix1/img/fullscreen.png
OpencvTuxiangchuliXuexiShouceChuyiFix1/img/loader.gif
OpencvTuxiangchuliXuexiShouceChuyiFix1/img/menu-icon.png
OpencvTuxiangchuliXuexiShouceChuyiFix1/img/save.png
OpencvTuxiangchuliXuexiShouceChuyiFix1/img/saved.png
OpencvTuxiangchuliXuexiShouceChuyiFix1/img/settings-s.png
OpencvTuxiangchuliXuexiShouceChuyiFix1/img/settings.png
OpencvTuxiangchuliXuexiShouceChuyiFix1/img/star.png
OpencvTuxiangchuliXuexiShouceChuyiFix1/js/__init__.py
OpencvTuxiangchuliXuexiShouceChuyiFix1/js/epub.js
OpencvTuxiangchuliXuexiShouceChuyiFix1/js/epub.min.js
OpencvTuxiangchuliXuexiShouceChuyiFix1/js/epub.min.map
OpencvTuxiangchuliXuexiShouceChuyiFix1/js/hooks.min.js
OpencvTuxiangchuliXuexiShouceChuyiFix1/js/hooks.min.map
opencv_tuxiangchuli_xuexi_shouce_chuyi_fix1-2025.3.25.1.dist-info/METADATA
opencv_tuxiangchuli_xuexi_shouce_chuyi_fix1-2025.3.25.1.dist-info/WHEEL
opencv_tuxiangchuli_xuexi_shouce_chuyi_fix1-2025.3.25.1.dist-info/entry_points.txt
opencv_tuxiangchuli_xuexi_shouce_chuyi_fix1-2025.3.25.1.dist-info/top_level.txt
opencv_tuxiangchuli_xuexi_shouce_chuyi_fix1-2025.3.25.1.dist-info/RECORD
